easyport/__init__.py
easyport/epconnector.py
easyport-0.1.3.dist-info/LICENSE
easyport-0.1.3.dist-info/METADATA
easyport-0.1.3.dist-info/WHEEL
easyport-0.1.3.dist-info/top_level.txt
easyport-0.1.3.dist-info/RECORD
