Metadata-Version: 2.1
Name: easyport
Version: 0.1.3
Summary: Connect to EasyPort Module from Festo Didactic
Author: Ferdinand List
Author-email: easyport@list.bayern
Classifier: Programming Language :: Python :: 3
Classifier: License :: OSI Approved :: MIT License
Classifier: Operating System :: POSIX :: Linux
Requires-Python: >=3.7
License-File: LICENSE
Requires-Dist: pyftdi
Requires-Dist: dill
